pyvda/__init__.py
pyvda/_version.py
pyvda/build.py
pyvda/com_base.py
pyvda/com_defns.py
pyvda/const.py
pyvda/pyvda.py
pyvda/utils.py
pyvda/winstring.py
pyvda-0.5.0.dist-info/LICENSE.txt
pyvda-0.5.0.dist-info/METADATA
pyvda-0.5.0.dist-info/WHEEL
pyvda-0.5.0.dist-info/top_level.txt
pyvda-0.5.0.dist-info/RECORD
